trie_global.py
appFolder/__init__.py
appFolder/app.py
appFolder/trieProject.py
trie_cli_global-0.2.0.dist-info/LICENSE
trie_cli_global-0.2.0.dist-info/METADATA
trie_cli_global-0.2.0.dist-info/WHEEL
trie_cli_global-0.2.0.dist-info/entry_points.txt
trie_cli_global-0.2.0.dist-info/top_level.txt
trie_cli_global-0.2.0.dist-info/RECORD
