Metadata-Version: 2.1
Name: trie-cli-global
Version: 0.2.0
Summary: A CLI that allows a user to update or see a data structure that is hosted globally. 
Home-page: UNKNOWN
Author: c25kenneth
License: UNKNOWN
Platform: UNKNOWN
Classifier: Programming Language :: Python :: 3
Classifier: License :: OSI Approved :: MIT License
Classifier: Operating System :: MacOS
Requires-Python: >=3.9.6
Requires-Dist: click
Requires-Dist: requests
